fablablib_python_ver1/ADC_fablab.py
fablablib_python_ver1/DAC_fablab.py
fablablib_python_ver1/DI_fablab.py
fablablib_python_ver1/DO_fablab.py
fablablib_python_ver1/FINS_fablab.py
fablablib_python_ver1/LCD_fablab.py
fablablib_python_ver1/LOG_data_fablab.py
fablablib_python_ver1/LORA_fablab.py
fablablib_python_ver1/MQTT_fablab.py
fablablib_python_ver1/OPCUA_falab.py
fablablib_python_ver1/QRcode_fablab.py
fablablib_python_ver1/RS232_fablab.py
fablablib_python_ver1/RS485_fablab.py
fablablib_python_ver1/__init__.py
fablablib_python_ver1/convert_time_fablab.py
fablablib_python_ver1/http_post_fablab.py
fablablib_python_ver1/json_payload_fablab.py
fablablib_python_ver1/led_7segment_fablab.py
fablablib_python_ver1/sparkplug_fablab.py
fablablib_python_ver1-0.0.1.dist-info/LICENSE
fablablib_python_ver1-0.0.1.dist-info/METADATA
fablablib_python_ver1-0.0.1.dist-info/WHEEL
fablablib_python_ver1-0.0.1.dist-info/top_level.txt
fablablib_python_ver1-0.0.1.dist-info/RECORD
