Metadata-Version: 2.1
Name: fablablib_python_ver1
Version: 0.0.1
Summary: For generating necessary modules fof FABLAB
Home-page: https://github.com/78-quangSky/fablablib_python_ver1
Author: 78-quangSky
Author-email: dangquang02530@gmail.com
Classifier: Programming Language :: Python :: 3
Classifier: License :: OSI Approved :: MIT License
Classifier: Operating System :: OS Independent
Requires-Python: >=3.7
License-File: LICENSE
